binio/__init__.py
binio/breader.py
binio/bwriter.py
binio/enums.py
binio/exceptions.py
binio/py.typed
pybinio-0.1.3.dist-info/LICENSE
pybinio-0.1.3.dist-info/METADATA
pybinio-0.1.3.dist-info/WHEEL
pybinio-0.1.3.dist-info/top_level.txt
pybinio-0.1.3.dist-info/zip-safe
pybinio-0.1.3.dist-info/RECORD
